{
  "api": "getThroughputCollect",
  "path": "/api/gateway/getThroughputCollect",
  "domain": "D2",
  "intent": "查询月度吞吐量汇总及同比",
  "params_sent": {
    "date": "2026-03",
    "yoyDate": "2025-03"
  },
  "status": "BIZ_ERROR",
  "http_status": 200,
  "error": "success=false, errorCode=103",
  "response_pattern": "PATTERN_B",
  "data_sample": {
    "success": false,
    "errorCode": 103,
    "errorInfo": "参数解析异常参数statisticType为必填项",
    "data": null,
    "space": 49,
    "jdbcQuerySpace": 0,
    "__more__": "...(3 more keys)"
  },
  "latency_ms": 64.0,
  "fetched_at": "20260416_211930",
  "base_url": "https://10.29.212.24:81",
  "data": null
}